biorad1sc_reader/__init__.py
biorad1sc_reader/cmd_bio1sc2tiff.py
biorad1sc_reader/cmd_bio1scmeta.py
biorad1sc_reader/cmd_bio1scread.py
biorad1sc_reader/constants.py
biorad1sc_reader/errors.py
biorad1sc_reader/parsing.py
biorad1sc_reader/reader.py
biorad1sc_reader-0.7.0.dist-info/LICENSE.txt
biorad1sc_reader-0.7.0.dist-info/METADATA
biorad1sc_reader-0.7.0.dist-info/WHEEL
biorad1sc_reader-0.7.0.dist-info/entry_points.txt
biorad1sc_reader-0.7.0.dist-info/top_level.txt
biorad1sc_reader-0.7.0.dist-info/RECORD
