Metadata-Version: 2.1
Name: biorad1sc-reader
Version: 0.7.0
Summary: Allows reading Bio-Rad *.1sc image/analysis files.
Home-page: https://github.com/itsayellow/biorad1sc_reader
Author: Matthew A. Clapp
Author-email: Matthew Clapp <itsayellow+dev@gmail.com>
License: MIT
Keywords: biorad,1sc,biology,scientific,imaging,image
Platform: UNKNOWN
Classifier: Development Status :: 4 - Beta
Classifier: Intended Audience :: Developers
Classifier: Intended Audience :: Science/Research
Classifier: Topic :: Multimedia :: Graphics
Classifier: Topic :: Scientific/Engineering :: Bio-Informatics
Classifier: Topic :: Scientific/Engineering :: Medical Science Apps.
Classifier: License :: OSI Approved :: MIT License
Classifier: Programming Language :: Python :: 3
Requires-Python: >=3.6
Requires-Dist: Pillow
